csedu/__init__.py
csedu/diagrams.py
csedu/imageprocessing.py
csedu-0.1.0.dist-info/LICENSE.txt
csedu-0.1.0.dist-info/METADATA
csedu-0.1.0.dist-info/WHEEL
csedu-0.1.0.dist-info/top_level.txt
csedu-0.1.0.dist-info/RECORD
