Metadata-Version: 2.1
Name: csedu
Version: 0.1.0
Summary: A package for computer science education containing modules for image processing and chart creation.
Home-page: https://github.com/henningmattes/csedu
Author: Henning Mattes
Author-email: henning_mattes@gmx.de
License: MIT with additional terms
Keywords: education computer science image processing charts computer science education
Classifier: Development Status :: 3 - Alpha
Classifier: Intended Audience :: Education
Classifier: License :: OSI Approved :: MIT License
Classifier: Programming Language :: Python :: 3
Classifier: Programming Language :: Python :: 3.7
Classifier: Programming Language :: Python :: 3.8
Classifier: Programming Language :: Python :: 3.9
Classifier: Topic :: Education
Classifier: Topic :: Software Development :: Libraries :: Python Modules
Requires-Python: >=3.7
License-File: LICENSE.txt
Requires-Dist: matplotlib
Requires-Dist: numpy
Requires-Dist: Pillow
